TP_RequestFlows/__init__.py
TP_RequestFlows-2025.7.1.dist-info/LICENSE
TP_RequestFlows-2025.7.1.dist-info/METADATA
TP_RequestFlows-2025.7.1.dist-info/WHEEL
TP_RequestFlows-2025.7.1.dist-info/top_level.txt
TP_RequestFlows-2025.7.1.dist-info/RECORD
