Metadata-Version: 2.1
Name: TP-RequestFlows
Version: 2025.7.1
Summary: A Python library for sending raw HTTP requests in a predefined sequence configured via a rules.json file. Supports automatic re-login when the session token expires
Home-page: https://github.com/tpcybersec/TP-RequestFlows
Author: TP Cyber Security
Author-email: tpcybersec2023@gmail.com
License: MIT
Keywords: TPCyberSec,TP-RequestFlows,Request Flows
Classifier: Programming Language :: Python :: 3
License-File: LICENSE
Requires-Dist: json-duplicate-keys>=2025.7.1
Requires-Dist: TP-HTTP-Request-Response-Parser>=2025.7.1
Requires-Dist: TP-Requests>=2025.7.1
